{
	"doi": "10.1016/j.jpowsour.2014.03.046",
	"url": "http://dx.doi.org/10.1016/j.jpowsour.2014.03.046",
	"publisher": "Elsevier BV",
	"volume": "262",
	"author": "Christian Fleischer, Wladislaw Waag, Hans-Martin Heyn, Dirk Uwe Sauer",
	"title": "On-line adaptive battery impedance parameter and state estimation considering physical principles in reduced order equivalent circuit battery models part 2. Parameter and state estimation",
	"journal": "Journal of Power Sources",
	"issn": "0378-7753",
}
